README.md
setup.py
global_forecast_validation/__init__.py
global_forecast_validation/command_line.py
global_forecast_validation/compress_netcdf.py
global_forecast_validation/extract_data.py
global_forecast_validation/validate_forecasts.py
global_forecast_validation.egg-info/PKG-INFO
global_forecast_validation.egg-info/SOURCES.txt
global_forecast_validation.egg-info/dependency_links.txt
global_forecast_validation.egg-info/entry_points.txt
global_forecast_validation.egg-info/requires.txt
global_forecast_validation.egg-info/top_level.txt