Metadata-Version: 2.1
Name: global-forecast-validation
Version: 0.2
Summary: Routines for forecast validation on a large scale.
Home-page: https://github.com/BYU-Hydroinformatics/Global_Forecast_Validation
Author: Wade Roberts
Author-email: waderoberts123@gmail.com
License: MIT
Keywords: hydrology,forecast validation,global
Platform: UNKNOWN
Classifier: Programming Language :: Python :: 3.6
Classifier: Programming Language :: Python :: 3.7
